LICENSE
README.md
setup.cfg
setup.py
tests/__init__.py
tests/test_german_loader.py
tests/test_vocabulary_parser.py
wilhelm_python_sdk/__init__.py
wilhelm_python_sdk/ancient_greek_loader.py
wilhelm_python_sdk/database_clients.py
wilhelm_python_sdk/database_manager.py
wilhelm_python_sdk/german_loader.py
wilhelm_python_sdk/german_parser.py
wilhelm_python_sdk/latin_loader.py
wilhelm_python_sdk/vocabulary_parser.py
wilhelm_python_sdk.egg-info/PKG-INFO
wilhelm_python_sdk.egg-info/SOURCES.txt
wilhelm_python_sdk.egg-info/dependency_links.txt
wilhelm_python_sdk.egg-info/not-zip-safe
wilhelm_python_sdk.egg-info/requires.txt
wilhelm_python_sdk.egg-info/top_level.txt